texttest-4.4.6.dist-info/licenses/LICENSE.txt
texttestlib/__init__.py
texttestlib/__main__.py
texttestlib/engine.py
texttestlib/jobprocess.py
texttestlib/logconfiggen.py
texttestlib/plugins.py
texttestlib/testmodel.py
texttestlib/texttest_version.py
texttestlib/utils.py
texttestlib/__pycache__/__init__.cpython-313.pyc
texttestlib/__pycache__/__main__.cpython-313.pyc
texttestlib/__pycache__/engine.cpython-313.pyc
texttestlib/__pycache__/jobprocess.cpython-313.pyc
texttestlib/__pycache__/plugins.cpython-313.pyc
texttestlib/__pycache__/testmodel.cpython-313.pyc
texttestlib/__pycache__/texttest_version.cpython-313.pyc
texttestlib/__pycache__/utils.cpython-313.pyc
texttestlib/default/__init__.py
texttestlib/default/actionrunner.py
texttestlib/default/colorer.py
texttestlib/default/comparefile.py
texttestlib/default/comparetest.py
texttestlib/default/console.py
texttestlib/default/database_data.py
texttestlib/default/fpdiff.py
texttestlib/default/performance.py
texttestlib/default/reconnect.py
texttestlib/default/rundependent.py
texttestlib/default/runtest.py
texttestlib/default/sandbox.py
texttestlib/default/scripts.py
texttestlib/default/storytext_interface.py
texttestlib/default/traffic.py
texttestlib/default/virtualdisplay.py
texttestlib/default/__pycache__/__init__.cpython-313.pyc
texttestlib/default/__pycache__/actionrunner.cpython-313.pyc
texttestlib/default/__pycache__/colorer.cpython-313.pyc
texttestlib/default/__pycache__/comparefile.cpython-313.pyc
texttestlib/default/__pycache__/comparetest.cpython-313.pyc
texttestlib/default/__pycache__/console.cpython-313.pyc
texttestlib/default/__pycache__/database_data.cpython-313.pyc
texttestlib/default/__pycache__/fpdiff.cpython-313.pyc
texttestlib/default/__pycache__/performance.cpython-313.pyc
texttestlib/default/__pycache__/reconnect.cpython-313.pyc
texttestlib/default/__pycache__/rundependent.cpython-313.pyc
texttestlib/default/__pycache__/runtest.cpython-313.pyc
texttestlib/default/__pycache__/sandbox.cpython-313.pyc
texttest-4.4.6.dist-info/METADATA
texttest-4.4.6.dist-info/WHEEL
texttest-4.4.6.dist-info/entry_points.txt
texttest-4.4.6.dist-info/top_level.txt
texttest-4.4.6.dist-info/RECORD
