Metadata-Version: 2.4
Name: TextTest
Version: 4.4.6
Summary: A tool for text-based Approval Testing
Author-email: Geoff Bache <geoff.bache@pobox.com>
Project-URL: Homepage, http://www.texttest.org
Project-URL: Documentation, https://texttest.sourceforge.net/index.php?page=documentation_4_3
Project-URL: Repository, https://github.com/texttest/texttest
Project-URL: Issues, https://github.com/texttest/texttest/issues/
Classifier: Development Status :: 5 - Production/Stable
Classifier: Environment :: Console
Classifier: Environment :: Win32 (MS Windows)
Classifier: Environment :: X11 Applications :: GTK
Classifier: Intended Audience :: Developers
Classifier: Intended Audience :: Information Technology
Classifier: License :: OSI Approved :: GNU Library or Lesser General Public License (LGPL)
Classifier: Operating System :: OS Independent
Classifier: Programming Language :: Python
Classifier: Topic :: Software Development :: Libraries :: Python Modules
Classifier: Topic :: Software Development :: Testing
Requires-Python: >=3.9
License-File: LICENSE.txt
Requires-Dist: psutil
Provides-Extra: graphs
Requires-Dist: matplotlib; extra == "graphs"
Dynamic: license-file
